sqids/__init__.py
sqids/constants.py
sqids/py.typed
sqids/sqids.py
sqids-0.5.1.dist-info/LICENSE
sqids-0.5.1.dist-info/METADATA
sqids-0.5.1.dist-info/WHEEL
sqids-0.5.1.dist-info/top_level.txt
sqids-0.5.1.dist-info/RECORD
