Metadata-Version: 2.1
Name: sqids
Version: 0.5.1
Summary: Generate YouTube-like ids from numbers.
License: MIT License
Project-URL: Homepage, https://sqids.org/python
Keywords: sqids,encode,generate,ids,hashids
Classifier: License :: OSI Approved :: MIT License
Classifier: Programming Language :: Python :: 3.6
Classifier: Programming Language :: Python :: 3.7
Classifier: Programming Language :: Python :: 3.8
Classifier: Programming Language :: Python :: 3.9
Classifier: Programming Language :: Python :: 3.10
Classifier: Programming Language :: Python :: 3.11
Classifier: Programming Language :: Python :: 3.12
Classifier: Programming Language :: Python :: 3.13
Requires-Python: >=3.6
License-File: LICENSE
